flask_statsd.py
Flask_StatsD-0.1.2.dist-info/LICENSE
Flask_StatsD-0.1.2.dist-info/METADATA
Flask_StatsD-0.1.2.dist-info/WHEEL
Flask_StatsD-0.1.2.dist-info/top_level.txt
Flask_StatsD-0.1.2.dist-info/RECORD
