Metadata-Version: 2.1
Name: Flask-StatsD
Version: 0.1.2
Summary: Access to statsd in your app.
Home-page: https://github.com/cyberdelia/flask-statsd
Author: Timothee Peignier
Author-email: timothee.peignier@tryphon.org
License: BSD
Platform: any
Classifier: Environment :: Web Environment
Classifier: Intended Audience :: Developers
Classifier: License :: OSI Approved :: BSD License
Classifier: Operating System :: OS Independent
Classifier: Programming Language :: Python
Classifier: Topic :: Software Development :: Libraries :: Python Modules
Requires-Dist: Flask
Requires-Dist: statsd
